LICENSE
README.md
setup.py
simpletts/__init__.py
simpletts.egg-info/PKG-INFO
simpletts.egg-info/SOURCES.txt
simpletts.egg-info/dependency_links.txt
simpletts.egg-info/requires.txt
simpletts.egg-info/top_level.txt
simpletts/models/__init__.py
simpletts/models/f5/__init__.py
simpletts/models/kokoro/__init__.py
simpletts/models/parler/__init__.py
simpletts/models/xtts/__init__.py
simpletts/simple/__init__.py