Metadata-Version: 2.2
Name: simpletts
Version: 0.0.3
Summary: A lightweight Python library for running TTS models with a unified API.
Home-page: https://github.com/fakerybakery/simpletts
Author: mrfakename
Author-email: me@mrfake.name
License: BSD-3-Clause
Project-URL: Bug Tracker, https://github.com/fakerybakery/simpletts/issues
Project-URL: Documentation, https://github.com/fakerybakery/simpletts/wiki
Project-URL: Source Code, https://github.com/fakerybakery/simpletts
Classifier: License :: OSI Approved :: BSD License
Classifier: Programming Language :: Python :: 3
Classifier: Programming Language :: Python :: 3.10
Classifier: Programming Language :: Python :: 3.11
License-File: LICENSE
Requires-Dist: torch
Requires-Dist: accelerate
Requires-Dist: torchaudio
Requires-Dist: cached-path
Requires-Dist: transformers[torch]
Requires-Dist: datasets
Requires-Dist: pydub
Requires-Dist: numpy
Requires-Dist: scipy
Requires-Dist: librosa
Requires-Dist: soundfile
Requires-Dist: tqdm
Requires-Dist: openphonemizer
Requires-Dist: click
Requires-Dist: txtsplit
Requires-Dist: munch
Requires-Dist: kokoro
Provides-Extra: xtts
Requires-Dist: tts; extra == "xtts"
Provides-Extra: f5
Requires-Dist: f5-tts; extra == "f5"
Provides-Extra: parler
Requires-Dist: parler-tts; extra == "parler"
Dynamic: author
Dynamic: author-email
Dynamic: classifier
Dynamic: description
Dynamic: description-content-type
Dynamic: home-page
Dynamic: license
Dynamic: project-url
Dynamic: provides-extra
Dynamic: requires-dist
Dynamic: summary
